eidl/__init__.py
eidl/params.py
eidl/Models/ExpertAttentionViT.py
eidl/Models/ExpertAttentionViTSubImages.py
eidl/Models/ExtensionModel.py
eidl/Models/ExtensionTimmViT.py
eidl/Models/ExtensionTimmViTSubimage.py
eidl/Models/ResNet.py
eidl/Models/ViT.py
eidl/Models/ViT_luci.py
eidl/Models/__init__.py
eidl/Models/ViT_pretrained/.gitignore
eidl/Models/ViT_pretrained/README.md
eidl/Models/ViT_pretrained/__init__.py
eidl/Models/ViT_pretrained/setup.py
eidl/Models/ViT_pretrained/examples/__init__.py
eidl/Models/ViT_pretrained/examples/imagenet/README.md
eidl/Models/ViT_pretrained/examples/imagenet/__init__.py
eidl/Models/ViT_pretrained/examples/imagenet/main.py
eidl/Models/ViT_pretrained/examples/simple/__init__.py
eidl/Models/ViT_pretrained/examples/simple/example.ipynb
eidl/Models/ViT_pretrained/examples/simple/imagenet-21k-labels.py
eidl/Models/ViT_pretrained/examples/simple/imagenet.synset.obtain_synset_list
eidl/Models/ViT_pretrained/examples/simple/img.jpg
eidl/Models/ViT_pretrained/examples/simple/img2.jpg
eidl/Models/ViT_pretrained/examples/simple/labels_map.txt
eidl/Models/ViT_pretrained/examples/simple/labels_map_21k.txt
eidl/Models/ViT_pretrained/jax_to_pytorch/README.md
eidl/Models/ViT_pretrained/jax_to_pytorch/__init__.py
eidl/Models/ViT_pretrained/jax_to_pytorch/convert.py
eidl/Models/ViT_pretrained/jax_to_pytorch/explore-conversion-21k.ipynb
eidl/Models/ViT_pretrained/jax_to_pytorch/explore-conversion.ipynb
eidl/Models/ViT_pretrained/jax_to_pytorch/jax_weights/download.sh
eidl/Models/ViT_pretrained/jax_to_pytorch/weights/.gitkeep
eidl/Models/ViT_pretrained/pytorch_pretrained_vit/__init__.py
eidl/Models/ViT_pretrained/pytorch_pretrained_vit/configs.py
eidl/Models/ViT_pretrained/pytorch_pretrained_vit/model.py
eidl/Models/ViT_pretrained/pytorch_pretrained_vit/transformer.py
eidl/Models/ViT_pretrained/pytorch_pretrained_vit/utils.py
eidl/datasets/OCTDataset.py
eidl/datasets/ODIRDatasets.py
eidl/datasets/__init__.py
eidl/examples/__init__.py
expert_informed_dl-0.0.23.dist-info/METADATA
expert_informed_dl-0.0.23.dist-info/WHEEL
expert_informed_dl-0.0.23.dist-info/licenses/LICENSE
expert_informed_dl-0.0.23.dist-info/RECORD
