Metadata-Version: 2.1
Name: expert-informed-dl
Version: 0.0.23
Summary: Deep learning image classificaiton informed by expert attention
Project-URL: Homepage, https://github.com/ApocalyVec/ExpertInformedDL
Project-URL: Bug Tracker, https://github.com/ApocalyVec/ExpertInformedDL/issues
Author-email: Ziheng 'Leo' Li <apocalyvec@gmail.com>
License-File: LICENSE
Classifier: License :: OSI Approved :: BSD License
Classifier: Operating System :: OS Independent
Classifier: Programming Language :: Python :: 3
Requires-Python: >=3.9
Requires-Dist: einops
Requires-Dist: gdown==4.6.0
Requires-Dist: graphviz
Requires-Dist: imageio
Requires-Dist: matplotlib
Requires-Dist: opencv-python
Requires-Dist: pandas
Requires-Dist: prettytable
Requires-Dist: scikit-learn
Requires-Dist: timm-eidl
Requires-Dist: toml
Requires-Dist: torchsummary
Requires-Dist: tqdm
